florence/__init__.py
florence_api-0.5.0.dist-info/LICENSE.txt
florence_api-0.5.0.dist-info/METADATA
florence_api-0.5.0.dist-info/WHEEL
florence_api-0.5.0.dist-info/top_level.txt
florence_api-0.5.0.dist-info/RECORD
